xapi/__init__.py
xapi/cli.py
xapi/connection.py
xapi/enums.py
xapi/exceptions.py
xapi/socket.py
xapi/stream.py
xapi/xapi.py
xapi_python-0.2.1.dist-info/LICENSE
xapi_python-0.2.1.dist-info/METADATA
xapi_python-0.2.1.dist-info/WHEEL
xapi_python-0.2.1.dist-info/entry_points.txt
xapi_python-0.2.1.dist-info/top_level.txt
xapi_python-0.2.1.dist-info/RECORD
