Metadata-Version: 2.1
Name: xapi-python
Version: 0.2.1
Summary: The xStation5 API Python library
Home-page: https://github.com/pawelkn/xapi-python
Author: Paweł Knioła
Author-email: Paweł Knioła <pawel@kniola.pl>
License: MIT License
Project-URL: Homepage, https://github.com/pawelkn/xapi-python
Project-URL: Bug Tracker, https://github.com/pawelkn/xapi-python/issues
Keywords: python,python3,bitcoin,trading,websocket,trading-api,forex,xapi,forex-trading,exchange-api,forex-data,xstation,xstation5,xtb,xopenhub,forex-api,xopenhub-api,xtb-api,xstation-api,x-trade-brokers,bfbcapital
Classifier: License :: OSI Approved :: MIT License
Classifier: Operating System :: OS Independent
Classifier: Programming Language :: Python :: 3.7
Classifier: Programming Language :: Python :: 3.8
Classifier: Programming Language :: Python :: 3.9
Classifier: Programming Language :: Python :: 3.10
Classifier: Programming Language :: Python :: 3.11
Classifier: Programming Language :: Python :: 3.12
Classifier: Programming Language :: Python :: 3.13
Requires-Python: >=3.7
License-File: LICENSE
Requires-Dist: websockets>=11.0.2
Requires-Dist: click>=8.1.8
